felix/__init__.py
felix_decorator-0.1.0a0.dist-info/LICENSE
felix_decorator-0.1.0a0.dist-info/METADATA
felix_decorator-0.1.0a0.dist-info/WHEEL
felix_decorator-0.1.0a0.dist-info/top_level.txt
felix_decorator-0.1.0a0.dist-info/RECORD
