Metadata-Version: 2.1
Name: felix-decorator
Version: 0.1.0a0
Summary: A collection of handy decorators for Python
Home-page: https://github.com/zzhengnan/felix
Author: Zhengnan Zhao
License: UNKNOWN
Platform: UNKNOWN
Classifier: Programming Language :: Python :: 3.7
Classifier: Programming Language :: Python :: 3.8
Classifier: Programming Language :: Python :: 3.9
Classifier: License :: OSI Approved :: MIT License
Classifier: Operating System :: OS Independent
Requires-Python: >=3.7
Provides-Extra: build
Requires-Dist: setuptools ; extra == 'build'
Requires-Dist: twine ; extra == 'build'
Requires-Dist: wheel ; extra == 'build'
Provides-Extra: dev
Requires-Dist: setuptools ; extra == 'dev'
Requires-Dist: twine ; extra == 'dev'
Requires-Dist: wheel ; extra == 'dev'
Requires-Dist: flake8 ; extra == 'dev'
Requires-Dist: mypy ; extra == 'dev'
Requires-Dist: pytest ; extra == 'dev'
Provides-Extra: qa
Requires-Dist: flake8 ; extra == 'qa'
Provides-Extra: test
Requires-Dist: mypy ; extra == 'test'
Requires-Dist: pytest ; extra == 'test'
